<annotation>
  <folder>images</folder>
  <filename>075c9a61ce0eb508.jpg</filename>
  <path>/Users/yash/Downloads/insect2/insect/images/075c9a61ce0eb508.jpg</path>
  <source>
    <database>OpenImages</database>
  </source>
  <size>
    <width>1017</width>
    <height>1024</height>
    <depth>3</depth>
  </size>
  <segmented>0</segmented>
  <object>
    <name>insect</name>
    <pose>Unspecified</pose>
    <truncated>0</truncated>
    <difficult>0</difficult>
    <bndbox>
      <xmin>236</xmin>
      <xmax>707</xmax>
      <ymin>168</ymin>
      <ymax>885</ymax>
    </bndbox>
  </object>
</annotation>
