<annotation>
  <folder>images</folder>
  <filename>203df1440f7b403c.jpg</filename>
  <path>/Users/yash/Downloads/insect2/insect/images/203df1440f7b403c.jpg</path>
  <source>
    <database>OpenImages</database>
  </source>
  <size>
    <width>1024</width>
    <height>640</height>
    <depth>3</depth>
  </size>
  <segmented>0</segmented>
  <object>
    <name>insect</name>
    <pose>Unspecified</pose>
    <truncated>0</truncated>
    <difficult>0</difficult>
    <bndbox>
      <xmin>127</xmin>
      <xmax>856</xmax>
      <ymin>0</ymin>
      <ymax>639</ymax>
    </bndbox>
  </object>
</annotation>
