<annotation>
  <folder>images</folder>
  <filename>5a8cf3aea60e9c24.jpg</filename>
  <path>/Users/yash/Downloads/insect2/insect/images/5a8cf3aea60e9c24.jpg</path>
  <source>
    <database>OpenImages</database>
  </source>
  <size>
    <width>1024</width>
    <height>532</height>
    <depth>3</depth>
  </size>
  <segmented>0</segmented>
  <object>
    <name>insect</name>
    <pose>Unspecified</pose>
    <truncated>0</truncated>
    <difficult>0</difficult>
    <bndbox>
      <xmin>38</xmin>
      <xmax>920</xmax>
      <ymin>5</ymin>
      <ymax>447</ymax>
    </bndbox>
  </object>
</annotation>
