<annotation>
  <folder>images</folder>
  <filename>c3fe92578eeacd4e.jpg</filename>
  <path>/Users/yash/Downloads/insect2/insect/images/c3fe92578eeacd4e.jpg</path>
  <source>
    <database>OpenImages</database>
  </source>
  <size>
    <width>876</width>
    <height>768</height>
    <depth>3</depth>
  </size>
  <segmented>0</segmented>
  <object>
    <name>insect</name>
    <pose>Unspecified</pose>
    <truncated>0</truncated>
    <difficult>0</difficult>
    <bndbox>
      <xmin>138</xmin>
      <xmax>776</xmax>
      <ymin>111</ymin>
      <ymax>718</ymax>
    </bndbox>
  </object>
</annotation>
