<annotation>
  <folder>images</folder>
  <filename>06f1d75cc0f21a20.jpg</filename>
  <path>/Users/yash/Downloads/insect2/insect/images/06f1d75cc0f21a20.jpg</path>
  <source>
    <database>OpenImages</database>
  </source>
  <size>
    <width>637</width>
    <height>1024</height>
    <depth>3</depth>
  </size>
  <segmented>0</segmented>
  <object>
    <name>insect</name>
    <pose>Unspecified</pose>
    <truncated>0</truncated>
    <difficult>0</difficult>
    <bndbox>
      <xmin>142</xmin>
      <xmax>525</xmax>
      <ymin>32</ymin>
      <ymax>952</ymax>
    </bndbox>
  </object>
</annotation>
