<annotation>
  <folder>images</folder>
  <filename>a44d39f878b61aa9.jpg</filename>
  <path>/Users/yash/Downloads/insect2/insect/images/a44d39f878b61aa9.jpg</path>
  <source>
    <database>OpenImages</database>
  </source>
  <size>
    <width>1024</width>
    <height>614</height>
    <depth>3</depth>
  </size>
  <segmented>0</segmented>
  <object>
    <name>insect</name>
    <pose>Unspecified</pose>
    <truncated>0</truncated>
    <difficult>0</difficult>
    <bndbox>
      <xmin>541</xmin>
      <xmax>670</xmax>
      <ymin>366</ymin>
      <ymax>467</ymax>
    </bndbox>
  </object>
</annotation>
