<annotation>
  <folder>images</folder>
  <filename>c98897c06c84b3bc.jpg</filename>
  <path>/Users/yash/Downloads/insect2/insect/images/c98897c06c84b3bc.jpg</path>
  <source>
    <database>OpenImages</database>
  </source>
  <size>
    <width>1024</width>
    <height>683</height>
    <depth>3</depth>
  </size>
  <segmented>0</segmented>
  <object>
    <name>insect</name>
    <pose>Unspecified</pose>
    <truncated>0</truncated>
    <difficult>0</difficult>
    <bndbox>
      <xmin>325</xmin>
      <xmax>367</xmax>
      <ymin>237</ymin>
      <ymax>259</ymax>
    </bndbox>
  </object>
  <object>
    <name>insect</name>
    <pose>Unspecified</pose>
    <truncated>0</truncated>
    <difficult>0</difficult>
    <bndbox>
      <xmin>387</xmin>
      <xmax>410</xmax>
      <ymin>251</ymin>
      <ymax>267</ymax>
    </bndbox>
  </object>
  <object>
    <name>insect</name>
    <pose>Unspecified</pose>
    <truncated>0</truncated>
    <difficult>0</difficult>
    <bndbox>
      <xmin>410</xmin>
      <xmax>444</xmax>
      <ymin>534</ymin>
      <ymax>548</ymax>
    </bndbox>
  </object>
  <object>
    <name>insect</name>
    <pose>Unspecified</pose>
    <truncated>0</truncated>
    <difficult>0</difficult>
    <bndbox>
      <xmin>422</xmin>
      <xmax>447</xmax>
      <ymin>494</ymin>
      <ymax>524</ymax>
    </bndbox>
  </object>
  <object>
    <name>insect</name>
    <pose>Unspecified</pose>
    <truncated>0</truncated>
    <difficult>0</difficult>
    <bndbox>
      <xmin>423</xmin>
      <xmax>452</xmax>
      <ymin>254</ymin>
      <ymax>263</ymax>
    </bndbox>
  </object>
  <object>
    <name>insect</name>
    <pose>Unspecified</pose>
    <truncated>0</truncated>
    <difficult>0</difficult>
    <bndbox>
      <xmin>424</xmin>
      <xmax>466</xmax>
      <ymin>604</ymin>
      <ymax>619</ymax>
    </bndbox>
  </object>
  <object>
    <name>insect</name>
    <pose>Unspecified</pose>
    <truncated>0</truncated>
    <difficult>0</difficult>
    <bndbox>
      <xmin>446</xmin>
      <xmax>478</xmax>
      <ymin>495</ymin>
      <ymax>501</ymax>
    </bndbox>
  </object>
  <object>
    <name>insect</name>
    <pose>Unspecified</pose>
    <truncated>0</truncated>
    <difficult>0</difficult>
    <bndbox>
      <xmin>473</xmin>
      <xmax>497</xmax>
      <ymin>553</ymin>
      <ymax>578</ymax>
    </bndbox>
  </object>
  <object>
    <name>insect</name>
    <pose>Unspecified</pose>
    <truncated>0</truncated>
    <difficult>0</difficult>
    <bndbox>
      <xmin>664</xmin>
      <xmax>691</xmax>
      <ymin>230</ymin>
      <ymax>239</ymax>
    </bndbox>
  </object>
  <object>
    <name>insect</name>
    <pose>Unspecified</pose>
    <truncated>0</truncated>
    <difficult>0</difficult>
    <bndbox>
      <xmin>666</xmin>
      <xmax>702</xmax>
      <ymin>229</ymin>
      <ymax>246</ymax>
    </bndbox>
  </object>
  <object>
    <name>insect</name>
    <pose>Unspecified</pose>
    <truncated>0</truncated>
    <difficult>0</difficult>
    <bndbox>
      <xmin>672</xmin>
      <xmax>698</xmax>
      <ymin>426</ymin>
      <ymax>444</ymax>
    </bndbox>
  </object>
  <object>
    <name>insect</name>
    <pose>Unspecified</pose>
    <truncated>0</truncated>
    <difficult>0</difficult>
    <bndbox>
      <xmin>708</xmin>
      <xmax>733</xmax>
      <ymin>210</ymin>
      <ymax>221</ymax>
    </bndbox>
  </object>
  <object>
    <name>insect</name>
    <pose>Unspecified</pose>
    <truncated>0</truncated>
    <difficult>0</difficult>
    <bndbox>
      <xmin>713</xmin>
      <xmax>737</xmax>
      <ymin>379</ymin>
      <ymax>408</ymax>
    </bndbox>
  </object>
  <object>
    <name>insect</name>
    <pose>Unspecified</pose>
    <truncated>0</truncated>
    <difficult>0</difficult>
    <bndbox>
      <xmin>747</xmin>
      <xmax>771</xmax>
      <ymin>347</ymin>
      <ymax>364</ymax>
    </bndbox>
  </object>
  <object>
    <name>insect</name>
    <pose>Unspecified</pose>
    <truncated>0</truncated>
    <difficult>0</difficult>
    <bndbox>
      <xmin>792</xmin>
      <xmax>809</xmax>
      <ymin>418</ymin>
      <ymax>451</ymax>
    </bndbox>
  </object>
  <object>
    <name>insect</name>
    <pose>Unspecified</pose>
    <truncated>0</truncated>
    <difficult>0</difficult>
    <bndbox>
      <xmin>797</xmin>
      <xmax>823</xmax>
      <ymin>404</ymin>
      <ymax>411</ymax>
    </bndbox>
  </object>
</annotation>
